mdtrj/__init__.py
mdtrj/settings.py
mdtrj/configuration/__init__.py
mdtrj/configuration/gyration.py
mdtrj/core/__init__.py
mdtrj/core/read_gsd.py
mdtrj/core/test.py
mdtrj/core/topology.py
mdtrj/core/trajectory.py
mdtrj/geometry/__init__.py
mdtrj/geometry/area.py
mdtrj/geometry/boundary.py
mdtrj/geometry/distance.py
mdtrj/geometry/rcm.py
mdtrj/util/__init__.py
mdtrj/util/gsd2lmp.py
mdtrj/util/linalg.py
mdtrj/util/square_wave.py
mdtrj/util/usefull_fit_funcs.py
mdtrj/util/visualize.py
mdtrj-0.0.2.dist-info/LICENSE
mdtrj-0.0.2.dist-info/METADATA
mdtrj-0.0.2.dist-info/WHEEL
mdtrj-0.0.2.dist-info/top_level.txt
mdtrj-0.0.2.dist-info/RECORD
